{"_locations":[{"ID":0,"Name":"","Description":"","Lng":108.45155954361,"Lat":11.9286759067223,"Price":null,"LocationType":0,"IsDeleted":false},{"ID":0,"Name":"126 ","Description":"","Lng":108.437606692314,"Lat":11.9488254945083,"Price":null,"LocationType":0,"IsDeleted":false},{"ID":0,"Name":"33","Description":"","Lng":108.433784544467,"Lat":11.947141477364,"Price":null,"LocationType":0,"IsDeleted":false},{"ID":0,"Name":"55*","Description":"","Lng":107.815178632736,"Lat":11.5560298919504,"Price":null,"LocationType":0,"IsDeleted":false},{"ID":0,"Name":"Á Đông ","Description":"","Lng":108.435927629471,"Lat":11.9463483390545,"Price":null,"LocationType":0,"IsDeleted":false},{"ID":0,"Name":"An Thủy ","Description":"","Lng":108.439637124538,"Lat":11.9459101111014,"Price":null,"LocationType":0,"IsDeleted":false},{"ID":0,"Name":"An Tiến","Description":"","Lng":108.427011966705,"Lat":11.9355367597934,"Price":null,"LocationType":0,"IsDeleted":false},{"ID":0,"Name":"Ana Mandara Villas Đà Lạt","Description":"","Lng":108.423593431877,"Lat":11.9440500206563,"Price":null,"LocationType":0,"IsDeleted":false},{"ID":0,"Name":"Anh Đào ","Description":"","Lng":108.435879349709,"Lat":11.9426063218529,"Price":null,"LocationType":0,"IsDeleted":false},{"ID":0,"Name":"Ánh Dương","Description":"","Lng":108.440170884132,"Lat":11.9440915887252,"Price":null,"LocationType":0,"IsDeleted":false},{"ID":0,"Name":"Anh Khoa ","Description":"","Lng":108.430906534195,"Lat":11.954577446021,"Price":null,"LocationType":0,"IsDeleted":false},{"ID":0,"Name":"Anh Quyên ","Description":"","Lng":108.46827507019,"Lat":11.9530554999403,"Price":null,"LocationType":0,"IsDeleted":false},{"ID":0,"Name":"BẮC HẢI 1","Description":"","Lng":107.534008026123,"Lat":11.3817313820785,"Price":null,"LocationType":0,"IsDeleted":false},{"ID":0,"Name":"Bạch Thủy","Description":"","Lng":108.440178930759,"Lat":11.944123078394,"Price":null,"LocationType":0,"IsDeleted":false},{"ID":0,"Name":"Bạch Thủy 2 ","Description":"","Lng":108.440208435059,"Lat":11.9462433743399,"Price":null,"LocationType":0,"IsDeleted":false},{"ID":0,"Name":"Bảo An *","Description":"","Lng":107.819244861603,"Lat":11.5413241209445,"Price":null,"LocationType":0,"IsDeleted":false},{"ID":0,"Name":"Bảo Ngọc ","Description":"","Lng":108.436115384102,"Lat":11.9410528184605,"Price":null,"LocationType":0,"IsDeleted":false},{"ID":0,"Name":"Bảo Phú **","Description":"","Lng":108.080191612244,"Lat":11.5867822917642,"Price":null,"LocationType":0,"IsDeleted":false},{"ID":0,"Name":"BẢO PHÚ\nĐC: 95 Klong Trao, xã Gung Ré\nĐT:  (+84-63)  3 770796\nNNKD: nhà hàng, tiệc cưới (600 khách)\n","Description":"","Lng":108.073625564575,"Lat":11.4754684530675,"Price":null,"LocationType":0,"IsDeleted":false},{"ID":0,"Name":"BẢO TÀNG LÂM ĐỒNG\nĐC: 04 Hùng Vương, Đà Lạt\nĐT: (+84-63) 3 822339\n","Description":"","Lng":108.460121154785,"Lat":11.9368278739796,"Price":null,"LocationType":0,"IsDeleted":false},{"ID":0,"Name":"Bảo Thịnh ","Description":"","Lng":108.436049669981,"Lat":11.9410948051558,"Price":null,"LocationType":0,"IsDeleted":false},{"ID":0,"Name":"Bảo Ti ","Description":"","Lng":108.438481092453,"Lat":11.9492348527615,"Price":null,"LocationType":0,"IsDeleted":false},{"ID":0,"Name":"BẢY HỒ","Description":"","Lng":107.62825012207,"Lat":11.4108432850736,"Price":null,"LocationType":0,"IsDeleted":false},{"ID":0,"Name":"BẾN THUYỀN DU LỊCH TUYỀN LÂM\nĐC: Khu du lịch Hồ Tuyền Lâm\n","Description":"","Lng":108.394187092781,"Lat":11.9877212731073,"Price":null,"LocationType":0,"IsDeleted":false},{"ID":0,"Name":"Bích Câu","Description":"","Lng":108.449800014496,"Lat":11.9481622541018,"Price":null,"LocationType":0,"IsDeleted":false},{"ID":0,"Name":"Bích Châu ","Description":"","Lng":108.433835506439,"Lat":11.9473586223522,"Price":null,"LocationType":0,"IsDeleted":false},{"ID":0,"Name":"BÍCH ĐÀO","Description":"","Lng":108.426985,"Lat":11.931758,"Price":null,"LocationType":0,"IsDeleted":false},{"ID":0,"Name":"BIỆT THỰ HẰNG NGA\n\n","Description":"","Lng":108.429957702755,"Lat":11.9349698178861,"Price":null,"LocationType":0,"IsDeleted":false},{"ID":0,"Name":"Billy","Description":"","Lng":108.428095579147,"Lat":11.9331204965482,"Price":null,"LocationType":0,"IsDeleted":false},{"ID":0,"Name":"Billy House","Description":"","Lng":108.433771133423,"Lat":11.9559504702056,"Price":null,"LocationType":0,"IsDeleted":false},{"ID":0,"Name":"Bình Yên ","Description":"","Lng":108.430938720703,"Lat":11.9435457672169,"Price":null,"LocationType":0,"IsDeleted":false},{"ID":0,"Name":"Blue Moon Hotel & Spa (Khách sạn Blue Moon)","Description":"","Lng":108.439674189163,"Lat":11.943312433173,"Price":null,"LocationType":0,"IsDeleted":false},{"ID":0,"Name":"Bông Hồng ","Description":"","Lng":108.430563211441,"Lat":11.9395885283915,"Price":null,"LocationType":0,"IsDeleted":false},{"ID":0,"Name":"Ca dao\nĐC:  18 Hồ Tùng Mậu - Đà Lạt\n","Description":"","Lng":108.439452052116,"Lat":11.9386565045025,"Price":null,"LocationType":0,"IsDeleted":false},{"ID":0,"Name":"Cà phê Cổ \nĐC: 26/1 đường Ba Tháng Tư - Đà Lạt\n","Description":"","Lng":108.446804657578,"Lat":11.9303373605899,"Price":null,"LocationType":0,"IsDeleted":false},{"ID":0,"Name":"Café de Palace\n ĐC: Hồ Tùng Mậu - Đà Lạt\n","Description":"","Lng":108.440138697624,"Lat":11.9388633781224,"Price":null,"LocationType":0,"IsDeleted":false},{"ID":0,"Name":"Cali*","Description":"","Lng":107.777810096741,"Lat":11.5302979825422,"Price":null,"LocationType":0,"IsDeleted":false},{"ID":0,"Name":"Camellia ","Description":"","Lng":108.459278941154,"Lat":11.9450940080532,"Price":null,"LocationType":0,"IsDeleted":false},{"ID":0,"Name":"CAO NGUYÊN","Description":"","Lng":108.442096710205,"Lat":11.9453301796062,"Price":null,"LocationType":0,"IsDeleted":false},{"ID":0,"Name":"CÁP TREO","Description":"","Lng":108.458383083344,"Lat":11.9479123084826,"Price":null,"LocationType":0,"IsDeleted":false},{"ID":0,"Name":"Châu Âu ","Description":"","Lng":108.435584306717,"Lat":11.9398614432696,"Price":null,"LocationType":0,"IsDeleted":false},{"ID":0,"Name":"Châu Út ","Description":"","Lng":108.434087634087,"Lat":11.9403836546259,"Price":null,"LocationType":0,"IsDeleted":false},{"ID":0,"Name":"Chốn xưa \nĐC: 01 Yagout - Đà Lạt\nĐT: (+84-63) 3560059","Description":"","Lng":108.428636044264,"Lat":11.9444910042748,"Price":null,"LocationType":0,"IsDeleted":false},{"ID":0,"Name":"Chương trình phát triển nông nghiệp công nghệ cao","Description":"","Lng":108.474655,"Lat":12.13332,"Price":null,"LocationType":0,"IsDeleted":false},{"ID":0,"Name":"CLB Thể dục thể hình Phù Đổng ","Description":"","Lng":108.442692160606,"Lat":11.9564342742484,"Price":null,"LocationType":0,"IsDeleted":false},{"ID":0,"Name":"Cỏ Hồng (Pink Grass)\nĐC: Đường Nguyễn Chí Thanh - Đà Lạt\n","Description":"","Lng":108.436753749847,"Lat":11.9410886820698,"Price":null,"LocationType":0,"IsDeleted":false},{"ID":0,"Name":"CƠM NIÊU NHƯ NGỌC","Description":"","Lng":108.439548611641,"Lat":11.9368068803021,"Price":null,"LocationType":0,"IsDeleted":false},{"ID":0,"Name":"Cụm công nghiệp Đinh Văn","Description":"","Lng":108.251538,"Lat":11.787963,"Price":null,"LocationType":0,"IsDeleted":false},{"ID":0,"Name":"Cụm công nghiệp Gia Hiệp","Description":"","Lng":108.179226,"Lat":11.629371,"Price":null,"LocationType":0,"IsDeleted":false},{"ID":0,"Name":"Cụm công nghiệp Ka Đô","Description":"","Lng":108.605976,"Lat":11.733932,"Price":null,"LocationType":0,"IsDeleted":false},{"ID":0,"Name":"Cụm công nghiệp Lộc Phát","Description":"","Lng":107.828894,"Lat":11.579934,"Price":null,"LocationType":0,"IsDeleted":false},{"ID":0,"Name":"Cụm công nghiệp Lộc Thắng","Description":"","Lng":107.817364,"Lat":11.678799,"Price":null,"LocationType":0,"IsDeleted":false},{"ID":0,"Name":"Cụm công nghiệp Phát Chi","Description":"","Lng":108.546925,"Lat":11.878438,"Price":null,"LocationType":0,"IsDeleted":false},{"ID":0,"Name":"Cung đàn xưa\nĐC: 8A Đường 3/2 - Đà Lạt\nĐT: 0913 113 855\n","Description":"","Lng":108.432120233774,"Lat":11.9413243104371,"Price":null,"LocationType":0,"IsDeleted":false},{"ID":0,"Name":"Cung tơ chiều\nĐC: 27K Lê Hồng Phong - Đà Lạt\nĐT: (+84-63) 3821158\n","Description":"","Lng":108.426742404699,"Lat":11.93331720554,"Price":null,"LocationType":0,"IsDeleted":false},{"ID":0,"Name":"Cưỡi voi ","Description":"","Lng":108.434629440308,"Lat":11.8967322377601,"Price":null,"LocationType":0,"IsDeleted":false},{"ID":0,"Name":"Đà Lạt Edensee","Description":"","Lng":108.437676429749,"Lat":11.8990743525658,"Price":null,"LocationType":0,"IsDeleted":false},{"ID":0,"Name":"Đà Lạt Hoa ","Description":"","Lng":108.439651876688,"Lat":11.9458550045421,"Price":null,"LocationType":0,"IsDeleted":false},{"ID":0,"Name":"ĐÀ LẠT HOUSE","Description":"","Lng":108.463393449783,"Lat":11.9477843834701,"Price":null,"LocationType":0,"IsDeleted":false},{"ID":0,"Name":"Đà Lạt Phố","Description":"","Lng":108.423026204109,"Lat":11.9408743749329,"Price":null,"LocationType":0,"IsDeleted":false},{"ID":0,"Name":"Đại Dương ","Description":"","Lng":108.435251712799,"Lat":11.9466684811828,"Price":null,"LocationType":0,"IsDeleted":false},{"ID":0,"Name":"Đài Liên ","Description":"","Lng":108.440092429519,"Lat":11.939715145184,"Price":null,"LocationType":0,"IsDeleted":false},{"ID":0,"Name":"Dalat Night\nĐC: 04 Đống Đa - Đà Lạt\n","Description":"","Lng":108.4426009655,"Lat":11.9252371485781,"Price":null,"LocationType":0,"IsDeleted":false},{"ID":0,"Name":"Dalat Palace","Description":"","Lng":108.439328,"Lat":11.937022,"Price":null,"LocationType":0,"IsDeleted":false},{"ID":0,"Name":"Dalat Palace Golf Club","Description":"","Lng":108.442611694336,"Lat":11.9555998347349,"Price":null,"LocationType":0,"IsDeleted":false},{"ID":0,"Name":"De lamour\nĐC: 6B Hồ Tùng Mậu - Đà Lạt\n","Description":"","Lng":108.444875478745,"Lat":11.937214288564,"Price":null,"LocationType":0,"IsDeleted":false},{"ID":0,"Name":"Đêm Vàng ","Description":"","Lng":108.437249958515,"Lat":11.9415671550296,"Price":null,"LocationType":0,"IsDeleted":false},{"ID":0,"Name":"Diễm xưa ","Description":"","Lng":108.459118679166,"Lat":11.9381058610294,"Price":null,"LocationType":0,"IsDeleted":false},{"ID":0,"Name":"Điện gió, điện mặt trời","Description":"","Lng":108.463154,"Lat":11.829718,"Price":null,"LocationType":0,"IsDeleted":false},{"ID":0,"Name":"Diệu Chi *","Description":"","Lng":107.812678813934,"Lat":11.5437628725478,"Price":null,"LocationType":0,"IsDeleted":false},{"ID":0,"Name":"Đồi Mộng Mơ *\nĐC: 05 Mai Anh Đào, Đà Lạt\nĐT: (+84-63) 3553218\nNNKD: Khách sạn (16 phòng)\n","Description":"","Lng":108.440852165222,"Lat":11.9744607972477,"Price":null,"LocationType":0,"IsDeleted":false},{"ID":0,"Name":"Đồng Nai","Description":"","Lng":108.443180322647,"Lat":11.9644331516747,"Price":null,"LocationType":0,"IsDeleted":false},{"ID":0,"Name":"DỰ ÁN ĐẦU TƯ NHÀ MÁY \u000bCHẾ BIẾN CÀ CHUA","Description":"","Lng":108.490028,"Lat":11.695152,"Price":null,"LocationType":0,"IsDeleted":false},{"ID":0,"Name":"Dự án khôi phục, cải tạo quốc lộ 20 đoạn từ Bảo Lộc - Đà Lạt, tỉnh Lâm Đồng (Km123+105,17–km 268).","Description":"","Lng":108.441124,"Lat":11.953349,"Price":null,"LocationType":0,"IsDeleted":false},{"ID":0,"Name":"Du lịch Bảo Lộc **","Description":"","Lng":107.803194522858,"Lat":11.5435962848729,"Price":null,"LocationType":0,"IsDeleted":false},{"ID":0,"Name":"Du lịch Công đoàn","Description":"","Lng":108.448812961578,"Lat":11.9404859974371,"Price":null,"LocationType":0,"IsDeleted":false},{"ID":0,"Name":"Dương Anh ","Description":"","Lng":108.440195024014,"Lat":11.9441112697686,"Price":null,"LocationType":0,"IsDeleted":false},{"ID":0,"Name":"Duy Đăng","Description":"","Lng":108.42620998621,"Lat":11.9397748453092,"Price":null,"LocationType":0,"IsDeleted":false},{"ID":0,"Name":"Duy Phương ","Description":"","Lng":108.433781862259,"Lat":11.9374366899172,"Price":null,"LocationType":0,"IsDeleted":false},{"ID":0,"Name":"Duy Quang*","Description":"","Lng":107.813848257065,"Lat":11.5382767192593,"Price":null,"LocationType":0,"IsDeleted":false},{"ID":0,"Name":"Duy Tân ","Description":"","Lng":108.429619073868,"Lat":11.9386333241534,"Price":null,"LocationType":0,"IsDeleted":false},{"ID":0,"Name":"Empress ","Description":"","Lng":108.43870639801,"Lat":11.9415304167356,"Price":null,"LocationType":0,"IsDeleted":false},{"ID":0,"Name":"Envy ","Description":"","Lng":108.437424302101,"Lat":11.9410475701231,"Price":null,"LocationType":0,"IsDeleted":false},{"ID":0,"Name":"Envy Lounge Bar Cafe\nĐC: 01 Nguyễn Thị Minh Khai - Đà Lạt\nĐT: (+84-63) 3837986","Description":"","Lng":108.437397480011,"Lat":11.9410546772333,"Price":null,"LocationType":0,"IsDeleted":false},{"ID":0,"Name":"ERO’S","Description":"","Lng":108.435884,"Lat":11.94089,"Price":null,"LocationType":0,"IsDeleted":false},{"ID":0,"Name":"Flamenco ","Description":"","Lng":108.453297615051,"Lat":11.9376886133534,"Price":null,"LocationType":0,"IsDeleted":false},{"ID":0,"Name":"GA XE LỬA ĐÀ LẠT\nĐC: 02 Quang Trung, Đà Lạt\nĐT: (+84-63) 3 834409\n","Description":"","Lng":108.456087112427,"Lat":11.9429750151845,"Price":null,"LocationType":0,"IsDeleted":false},{"ID":0,"Name":"Galy","Description":"","Lng":108.435734510422,"Lat":11.9399139268685,"Price":null,"LocationType":0,"IsDeleted":false},{"ID":0,"Name":"Gia Hảo 1 *","Description":"","Lng":107.810710072517,"Lat":11.547895586676,"Price":null,"LocationType":0,"IsDeleted":false},{"ID":0,"Name":"Gia Nguyễn\n","Description":"","Lng":108.436099290848,"Lat":11.9400188940357,"Price":null,"LocationType":0,"IsDeleted":false},{"ID":0,"Name":"Góc phố \nĐC: 84 Phan Đình Phùng - Đà Lạt\n","Description":"","Lng":108.434746786952,"Lat":11.9454829256218,"Price":null,"LocationType":0,"IsDeleted":false},{"ID":0,"Name":"Golf 1 ","Description":"","Lng":108.443191051483,"Lat":11.9462328778662,"Price":null,"LocationType":0,"IsDeleted":false},{"ID":0,"Name":"Golf 3","Description":"","Lng":108.437348,"Lat":11.941866,"Price":null,"LocationType":0,"IsDeleted":false},{"ID":0,"Name":"Hà Giang *","Description":"","Lng":107.814301550388,"Lat":11.5530541362568,"Price":null,"LocationType":0,"IsDeleted":false},{"ID":0,"Name":"HÀ NỘI 4","Description":"","Lng":108.057768344879,"Lat":11.5744643948271,"Price":null,"LocationType":0,"IsDeleted":false},{"ID":0,"Name":"Hải Duyên ","Description":"","Lng":108.430268168449,"Lat":11.9392710020815,"Price":null,"LocationType":0,"IsDeleted":false},{"ID":0,"Name":"HẢI MẬP\nĐC: 27 Lê Hồng Phong, P.4\nĐT: 0982012049 \nNNKD: nhà hàng (300 khách)\n","Description":"","Lng":108.426736369729,"Lat":11.9333447600859,"Price":null,"LocationType":0,"IsDeleted":false},{"ID":0,"Name":"Hải Sơn ","Description":"","Lng":108.437338471413,"Lat":11.9410160800968,"Price":null,"LocationType":0,"IsDeleted":false},{"ID":0,"Name":"Hải Sơn *","Description":"","Lng":108.367273807526,"Lat":11.7243825383,"Price":null,"LocationType":0,"IsDeleted":false},{"ID":0,"Name":"Hải Uyên *","Description":"","Lng":108.434768915176,"Lat":11.9405332325676,"Price":null,"LocationType":0,"IsDeleted":false},{"ID":0,"Name":"Hàng Châu *","Description":"","Lng":107.800297737122,"Lat":11.5414082161803,"Price":null,"LocationType":0,"IsDeleted":false},{"ID":0,"Name":"HỒ NAM PHƯƠNG 2","Description":"","Lng":107.815579,"Lat":11.569585,"Price":null,"LocationType":0,"IsDeleted":false},{"ID":0,"Name":"Hoa Viên Quán *","Description":"","Lng":107.779344320297,"Lat":11.5319893931411,"Price":null,"LocationType":0,"IsDeleted":false},{"ID":0,"Name":"Hoa Violet ngày thứ tư","Description":"","Lng":108.45490694046,"Lat":11.9418033296576,"Price":null,"LocationType":0,"IsDeleted":false},{"ID":0,"Name":"Hoan Hỷ *","Description":"","Lng":108.430032134056,"Lat":11.9390007107973,"Price":null,"LocationType":0,"IsDeleted":false},{"ID":0,"Name":"HOÀN KIỆT\nĐC: 08 Pasteur, P.4\nĐT: (+84-63)  3 586363\nNNKD: nhà hàng (300 khách)","Description":"","Lng":108.429549336433,"Lat":11.936726076484,"Price":null,"LocationType":0,"IsDeleted":false},{"ID":0,"Name":"Hoàng Anh Đất Xanh","Description":"","Lng":108.459658,"Lat":11.945099,"Price":null,"LocationType":0,"IsDeleted":false},{"ID":0,"Name":"HOÀNG MINH\nĐC: 29 Pasteur, P.4\nĐT: (+84-63) 2211345\nNNKD: nhà hàng, tiệc cưới (600 khách)","Description":"","Lng":108.42664450407,"Lat":11.9340303427801,"Price":null,"LocationType":0,"IsDeleted":false},{"ID":0,"Name":"Hoàng Thảo*","Description":"","Lng":108.434736728668,"Lat":11.9397144891386,"Price":null,"LocationType":0,"IsDeleted":false},{"ID":0,"Name":"Hoàng Thu *","Description":"","Lng":108.430235981941,"Lat":11.9483374127053,"Price":null,"LocationType":0,"IsDeleted":false},{"ID":0,"Name":"HOÀNG TUẤN\nĐC: 07 Huỳnh Thúc Kháng, P.4\nĐT: (+84-63) 3545779\nNNKD: nhà hàng (40 khách)","Description":"","Lng":108.430160880089,"Lat":11.9352237117841,"Price":null,"LocationType":0,"IsDeleted":false},{"ID":0,"Name":"Hoàng Việt 2*\n","Description":"","Lng":108.436469435692,"Lat":11.9413414768593,"Price":null,"LocationType":0,"IsDeleted":false},{"ID":0,"Name":"Hồng Hà","Description":"","Lng":108.435859233141,"Lat":11.9407011796319,"Price":null,"LocationType":0,"IsDeleted":false},{"ID":0,"Name":"Hồng Hải","Description":"","Lng":108.440208435059,"Lat":11.9440830602725,"Price":null,"LocationType":0,"IsDeleted":false},{"ID":0,"Name":"Hồng Hoa","Description":"","Lng":108.439543247223,"Lat":11.9483636536848,"Price":null,"LocationType":0,"IsDeleted":false},{"ID":0,"Name":"HỒNG LOAN","Description":"","Lng":108.437734965607,"Lat":11.9424328517251,"Price":null,"LocationType":0,"IsDeleted":false},{"ID":0,"Name":"Hồng Tâm","Description":"","Lng":108.435777425766,"Lat":11.9420342557616,"Price":null,"LocationType":0,"IsDeleted":false},{"ID":0,"Name":"Hồng Thái *","Description":"","Lng":107.791457176208,"Lat":11.5379602908478,"Price":null,"LocationType":0,"IsDeleted":false},{"ID":0,"Name":"HỒNG VÂN","Description":"","Lng":108.442289829254,"Lat":11.9536222946534,"Price":null,"LocationType":0,"IsDeleted":false},{"ID":0,"Name":"Hồng Vân ","Description":"","Lng":108.442445397377,"Lat":11.9536117984658,"Price":null,"LocationType":0,"IsDeleted":false},{"ID":0,"Name":"HP ","Description":"","Lng":108.430949449539,"Lat":11.9334478709725,"Price":null,"LocationType":0,"IsDeleted":false},{"ID":0,"Name":"Hùng Phong ","Description":"","Lng":108.441013097763,"Lat":11.9348754550236,"Price":null,"LocationType":0,"IsDeleted":false},{"ID":0,"Name":"Hương Bình *","Description":"","Lng":107.818075418472,"Lat":11.5346174447498,"Price":null,"LocationType":0,"IsDeleted":false},{"ID":0,"Name":"Hướng Dương","Description":"","Lng":108.431088924408,"Lat":11.9429684548093,"Price":null,"LocationType":0,"IsDeleted":false},{"ID":0,"Name":"Hương Trà *","Description":"","Lng":107.822340130806,"Lat":11.5429335055691,"Price":null,"LocationType":0,"IsDeleted":false},{"ID":0,"Name":"Hương Trà 1 ","Description":"","Lng":108.439273685217,"Lat":11.9420093262484,"Price":null,"LocationType":0,"IsDeleted":false},{"ID":0,"Name":"Hữu Nghị 1","Description":"","Lng":108.430571258068,"Lat":11.9397144891386,"Price":null,"LocationType":0,"IsDeleted":false},{"ID":0,"Name":"Hữu Nghị 2*\n","Description":"","Lng":108.433363437653,"Lat":11.9416143899717,"Price":null,"LocationType":0,"IsDeleted":false},{"ID":0,"Name":"Huy Tân *","Description":"","Lng":107.807102501392,"Lat":11.5433913042902,"Price":null,"LocationType":0,"IsDeleted":false},{"ID":0,"Name":"Huỳnh Gia Bảo *","Description":"","Lng":107.81048476696,"Lat":11.5482156583214,"Price":null,"LocationType":0,"IsDeleted":false},{"ID":0,"Name":"Huỳnh Gia Bảo 2 *","Description":"","Lng":107.806273698807,"Lat":11.5416720812437,"Price":null,"LocationType":0,"IsDeleted":false},{"ID":0,"Name":"Juno Phương*","Description":"","Lng":108.435696959496,"Lat":11.9419922692119,"Price":null,"LocationType":0,"IsDeleted":false},{"ID":0,"Name":"KARAOKE Điểm hẹn \nĐC: 17 Nguyễn Trãi - Đà Lạt\nĐT: (+84-63) 3577567\n","Description":"","Lng":108.452169075608,"Lat":11.940969391749,"Price":null,"LocationType":0,"IsDeleted":false},{"ID":0,"Name":"KARAOKE Diễm Quỳnh\nĐC: 18 Yersin -  Đà Lạt\nĐT: (+84-63) 3833651\n","Description":"","Lng":108.451471701264,"Lat":11.9403395903747,"Price":null,"LocationType":0,"IsDeleted":false},{"ID":0,"Name":"KARAOKE Quỳnh Hương\nĐC: 3/2 Cô Giang - Đà Lạt\nĐT: (+84-63) 3810200\n","Description":"","Lng":108.459639698267,"Lat":11.9484238985874,"Price":null,"LocationType":0,"IsDeleted":false},{"ID":0,"Name":"KDL LÀNG CÙ LẦN","Description":"","Lng":108.394085168839,"Lat":11.9870066375804,"Price":null,"LocationType":0,"IsDeleted":false},{"ID":0,"Name":"KDL MINH TÂM\nĐC: 20A Khe Sanh, Đà Lạt\nĐT: (+84-63) 3 822447\nNNKD: Tham quan, khách sạn, nhà hàng, sân tennis\n","Description":"","Lng":108.45909923315,"Lat":11.9381372420491,"Price":null,"LocationType":0,"IsDeleted":false},{"ID":0,"Name":"KDL TRÚC LÂM VIÊN","Description":"","Lng":108.432484,"Lat":11.828185,"Price":null,"LocationType":0,"IsDeleted":false},{"ID":0,"Name":"Khả Hân *","Description":"","Lng":108.370631933212,"Lat":11.7377603241375,"Price":null,"LocationType":0,"IsDeleted":false},{"ID":0,"Name":"Khải Hòa *","Description":"","Lng":108.374183177948,"Lat":11.7367770861885,"Price":null,"LocationType":0,"IsDeleted":false},{"ID":0,"Name":"Khải Hoàng *","Description":"","Lng":108.438749313354,"Lat":11.9493922980786,"Price":null,"LocationType":0,"IsDeleted":false},{"ID":0,"Name":"Khánh Hồng *","Description":"","Lng":108.434176146984,"Lat":11.939803711299,"Price":null,"LocationType":0,"IsDeleted":false},{"ID":0,"Name":"Khánh Vi Vân *","Description":"","Lng":108.432478308678,"Lat":11.93639225484,"Price":null,"LocationType":0,"IsDeleted":false},{"ID":0,"Name":"Khoa Đạt *","Description":"","Lng":108.074741363525,"Lat":11.5750316415794,"Price":null,"LocationType":0,"IsDeleted":false},{"ID":0,"Name":"KHÔNG TÊN\nĐC: 01 Triệu Việt Vương, P.4\nĐT: (+84-63) 3822702\nNNKD: nhà hàng (200 khách","Description":"","Lng":108.427047505975,"Lat":11.9320234503668,"Price":null,"LocationType":0,"IsDeleted":false},{"ID":0,"Name":"Khu công nghệ thông tin tập trung tỉnh Lâm Đồng","Description":"","Lng":108.521037,"Lat":12.181035,"Price":null,"LocationType":0,"IsDeleted":false},{"ID":0,"Name":"Khu công nghiệp Lộc Sơn giai đoạn 2","Description":"","Lng":107.828743,"Lat":11.524727,"Price":null,"LocationType":0,"IsDeleted":false},{"ID":0,"Name":"Khu công nghiệp Phú Hội giai đoạn 2","Description":"","Lng":108.35638,"Lat":11.672074,"Price":null,"LocationType":0,"IsDeleted":false},{"ID":0,"Name":"Khu công nghiệp và đô thị Tân Phú","Description":"","Lng":108.291836,"Lat":11.73326,"Price":null,"LocationType":0,"IsDeleted":false},{"ID":0,"Name":"KHU DÃ NGOẠI ĐÁ TIÊN","Description":"","Lng":108.436517715454,"Lat":11.9014932153313,"Price":null,"LocationType":0,"IsDeleted":false},{"ID":0,"Name":"KHU DÃ NGOẠI NAM QUA\nĐC: Khu du lịch Hồ Tuyền Lâm\n","Description":"","Lng":108.394042253494,"Lat":11.988338829498,"Price":null,"LocationType":0,"IsDeleted":false},{"ID":0,"Name":"KHU DÃ NGOẠI NAM QUA\nĐC: Khu du lịch Hồ Tuyền Lâm\nNNKD: Tham quan\n","Description":"","Lng":108.437397480011,"Lat":11.8964295339456,"Price":null,"LocationType":0,"IsDeleted":false},{"ID":0,"Name":"KHU DI TÍCH DINH III\nĐC: 01 Triệu Việt Vương, Đà Lạt\nĐT: (+84-63) 3 540213\nNNKD: Tham quan\n","Description":"","Lng":108.427030742168,"Lat":11.9320018002632,"Price":null,"LocationType":0,"IsDeleted":false},{"ID":0,"Name":"Khu đô thị mới Liên Khương – Prenn","Description":"","Lng":108.310661,"Lat":11.648874,"Price":null,"LocationType":0,"IsDeleted":false},{"ID":0,"Name":"KHU DU LỊCH CÁP TREO","Description":"","Lng":108.44445,"Lat":11.923665,"Price":null,"LocationType":0,"IsDeleted":false},{"ID":0,"Name":"KHU DU LỊCH DÃ NGOẠI TUYỀN LÂM","Description":"","Lng":108.431404,"Lat":11.900443,"Price":null,"LocationType":0,"IsDeleted":false},{"ID":0,"Name":"Khu du lịch Đamb'ri **","Description":"","Lng":107.776930332184,"Lat":11.5305492104271,"Price":null,"LocationType":0,"IsDeleted":false},{"ID":0,"Name":"Khu du lịch Đan Kia - Đà Lạt","Description":"","Lng":108.47683,"Lat":12.128621,"Price":null,"LocationType":0,"IsDeleted":false},{"ID":0,"Name":"KHU DU LỊCH ĐARAHOA – NÚI VOI","Description":"","Lng":108.439693450928,"Lat":11.8980917756911,"Price":null,"LocationType":0,"IsDeleted":false},{"ID":0,"Name":"KHU DU LỊCH ĐỒI MỘNG MƠ\nĐC: 05 Mai Anh Đào, Đà Lạt\nĐT: (+84-63) 3 553218\nNNKD: Tham quan, nhà hàng, sân golf mini, biểu diễn cồng chiêng, massage .\n","Description":"","Lng":108.440657034516,"Lat":11.9744274525769,"Price":null,"LocationType":0,"IsDeleted":false},{"ID":0,"Name":"KHU DU LỊCH HỒ THAN THỞ","Description":"","Lng":108.47528860315,"Lat":11.959436822543,"Price":null,"LocationType":0,"IsDeleted":false},{"ID":0,"Name":"KHU DU LỊCH LANGBIANG","Description":"","Lng":108.424501,"Lat":12.019273,"Price":null,"LocationType":0,"IsDeleted":false},{"ID":0,"Name":"KHU DU LỊCH THÁC CAM LY","Description":"","Lng":108.420371209822,"Lat":11.9420025235451,"Price":null,"LocationType":0,"IsDeleted":false},{"ID":0,"Name":"KHU DU LỊCH THÁC ĐAMB’RI","Description":"","Lng":107.742135,"Lat":11.641203,"Price":null,"LocationType":0,"IsDeleted":false},{"ID":0,"Name":"KHU DU LỊCH THÁC ĐATANLA","Description":"","Lng":108.448827,"Lat":11.901199,"Price":null,"LocationType":0,"IsDeleted":false},{"ID":0,"Name":"KHU DU LỊCH THÁC GOUGAH\nĐC:   Xã Phú Hội - Huyện Đức Trọng\nĐT: (+84-63) 3 678333\nNNKD: Tham quan\n","Description":"","Lng":108.353862762451,"Lat":11.7078517505254,"Price":null,"LocationType":0,"IsDeleted":false},{"ID":0,"Name":"KHU DU LỊCH THÁC HANG CỌP\nĐC: xã Xuân Thọ, Đà Lạt\nĐT: (+84-63) 3 700802\nNNKD: Tham quan\n","Description":"","Lng":108.454976007342,"Lat":11.9421082789042,"Price":null,"LocationType":0,"IsDeleted":false},{"ID":0,"Name":"KHU DU LỊCH THÁC PONGOUR","Description":"","Lng":108.263898,"Lat":11.68981,"Price":null,"LocationType":0,"IsDeleted":false},{"ID":0,"Name":"KHU DU LỊCH THÁC PRENN","Description":"","Lng":108.472456,"Lat":11.874218,"Price":null,"LocationType":0,"IsDeleted":false},{"ID":0,"Name":"KHU DU LỊCH THUNG LŨNG TÌNH YÊU\nĐC: 07 Mai Anh Đào, Đà Lạt\nĐT: (+84-63) 3 554311\nNNKD: Tham quan, vui chơi giải trí (cưỡi ngựa, tổ chức picnic, cắm trại..)\n","Description":"","Lng":108.453107848763,"Lat":11.9780161926678,"Price":null,"LocationType":0,"IsDeleted":false},{"ID":0,"Name":"KHU DU LỊCH THUNG LŨNG VÀNG\nĐC: Đường Ankroet, xã Lát, huyện Lạc Dương\nĐT: (+84-63) 2240689\n","Description":"","Lng":108.395018577576,"Lat":11.9848532085745,"Price":null,"LocationType":0,"IsDeleted":false},{"ID":0,"Name":"KHU TRIỂN LÃM TRANH THÊU XQ\nĐC: 258 Mai Anh Đào, Đà Lạt\nĐT: (+84-63) 3 831343\n","Description":"","Lng":108.447504043579,"Lat":11.9773511653202,"Price":null,"LocationType":0,"IsDeleted":false},{"ID":0,"Name":"Kiều Thanh *","Description":"","Lng":108.435868620872,"Lat":11.9408428848864,"Price":null,"LocationType":0,"IsDeleted":false},{"ID":0,"Name":"KIM HUÊ ĐÔ","Description":"","Lng":108.434028,"Lat":11.94364,"Price":null,"LocationType":0,"IsDeleted":false},{"ID":0,"Name":"Kim Vân *","Description":"","Lng":108.438741266727,"Lat":11.9494775809205,"Price":null,"LocationType":0,"IsDeleted":false},{"ID":0,"Name":"KS Ngọc Lan","Description":"","Lng":108.436635110451,"Lat":11.9407532947728,"Price":null,"LocationType":0,"IsDeleted":false},{"ID":0,"Name":"Kỷ niệm **","Description":"","Lng":107.823600769043,"Lat":11.5352597532475,"Price":null,"LocationType":0,"IsDeleted":false},{"ID":0,"Name":"La Pensee","Description":"","Lng":108.439725637436,"Lat":11.9457815291123,"Price":null,"LocationType":0,"IsDeleted":false},{"ID":0,"Name":"La Sapinette","Description":"","Lng":108.463832,"Lat":11.949119,"Price":null,"LocationType":0,"IsDeleted":false},{"ID":0,"Name":"La Vy ","Description":"","Lng":108.463683128357,"Lat":11.9506203684099,"Price":null,"LocationType":0,"IsDeleted":false},{"ID":0,"Name":"Ladophar*","Description":"","Lng":108.435600399971,"Lat":11.9429264684044,"Price":null,"LocationType":0,"IsDeleted":false},{"ID":0,"Name":"Lan Hương Cát *","Description":"","Lng":108.463897705078,"Lat":11.9443959887039,"Price":null,"LocationType":0,"IsDeleted":false},{"ID":0,"Name":"Làng đại học quốc tế","Description":"","Lng":108.470707,"Lat":12.122243,"Price":null,"LocationType":0,"IsDeleted":false},{"ID":0,"Name":"LÀNG DU LỊCH RỪNG MAĐAGUI","Description":"","Lng":107.537692,"Lat":11.393332,"Price":null,"LocationType":0,"IsDeleted":false},{"ID":0,"Name":"Làng du lịch Rừng Mađagui ***","Description":"","Lng":107.647047042847,"Lat":11.4106566123943,"Price":null,"LocationType":0,"IsDeleted":false},{"ID":0,"Name":"Lập Trường Sơn *","Description":"","Lng":108.435619175434,"Lat":11.9468862825783,"Price":null,"LocationType":0,"IsDeleted":false},{"ID":0,"Name":"Larry's Bar","Description":"","Lng":108.439288437366,"Lat":11.9369013518377,"Price":null,"LocationType":0,"IsDeleted":false},{"ID":0,"Name":"Lê Phương*","Description":"","Lng":108.434699177742,"Lat":11.9398404498272,"Price":null,"LocationType":0,"IsDeleted":false},{"ID":0,"Name":"LIÊN ĐÔ","Description":"","Lng":107.797508239746,"Lat":11.5402776915961,"Price":null,"LocationType":0,"IsDeleted":false},{"ID":0,"Name":"Linh Phương *","Description":"","Lng":107.819234132767,"Lat":11.5419024394296,"Price":null,"LocationType":0,"IsDeleted":false},{"ID":0,"Name":"LOAN\nĐC: Ngã 3 Phi Nôm\nĐT: (+84-63) 2 245651\nNNKD: Nhà hàng (250 khách)\n","Description":"","Lng":108.411650955677,"Lat":11.7836666496187,"Price":null,"LocationType":0,"IsDeleted":false},{"ID":0,"Name":"LONG HOA","Description":"","Lng":108.440041,"Lat":11.939704,"Price":null,"LocationType":0,"IsDeleted":false},{"ID":0,"Name":"LONG NGA","Description":"","Lng":108.459101915359,"Lat":11.9486765771698,"Price":null,"LocationType":0,"IsDeleted":false},{"ID":0,"Name":"Long Vương*","Description":"","Lng":108.43644797802,"Lat":11.9416038933186,"Price":null,"LocationType":0,"IsDeleted":false},{"ID":0,"Name":"M.I.C ","Description":"","Lng":108.45019698143,"Lat":11.9403423238643,"Price":null,"LocationType":0,"IsDeleted":false},{"ID":0,"Name":"Mai Hoa *","Description":"","Lng":108.371479511261,"Lat":11.7291506975631,"Price":null,"LocationType":0,"IsDeleted":false},{"ID":0,"Name":"Mái Nhà Hồng *","Description":"","Lng":108.43181848526,"Lat":11.941666873231,"Price":null,"LocationType":0,"IsDeleted":false},{"ID":0,"Name":"Mai Vàng * * *\nĐC: A1 – A2  Hải Thượng, Đà Lạt\nĐT: (+84-63) 3 511162\nFax: (+84-63) 511162\nWebsite: www.hotelmaivang.com\nEmail: maivanghotel@yahoo.com\nNNKD: Khách sạn (50 phòng), nhà hàng,  hội nghị, quầy bar dịch vụ, đưa đón sân bay, tour tham quan …\n","Description":"","Lng":108.430897817016,"Lat":11.943891388683,"Price":null,"LocationType":0,"IsDeleted":false},{"ID":0,"Name":"Máng trượt","Description":"","Lng":108.448979258537,"Lat":11.9011720356878,"Price":null,"LocationType":0,"IsDeleted":false},{"ID":0,"Name":"Miền Nhiệt Đới 2\nĐC: 14B Thủ Khoa Huân, Đà Lạt\nĐT: (+84-63) 3 513123\nNNKD: Khách sạn (31 phòng)\n","Description":"","Lng":108.434068858624,"Lat":11.9404399650416,"Price":null,"LocationType":0,"IsDeleted":false},{"ID":0,"Name":"Minh Châu *\nĐC: 15 Nguyễn Chí Thanh, Đà Lạt\nĐT: (+84-63) 3 837053\nNNKD: Khách sạn (19 phòng)\n","Description":"","Lng":108.435426056385,"Lat":11.9397911370859,"Price":null,"LocationType":0,"IsDeleted":false},{"ID":0,"Name":"Minh Đức *\nĐC: A5 Hải Thượng, Đà Lạt\nĐT: (+84-63) 3 815514\nNNKD: Khách sạn (17 phòng)\n","Description":"","Lng":108.431031256914,"Lat":11.9429578488557,"Price":null,"LocationType":0,"IsDeleted":false},{"ID":0,"Name":"Minh Hưng *","Description":"","Lng":108.373453617096,"Lat":11.7322706093009,"Price":null,"LocationType":0,"IsDeleted":false},{"ID":0,"Name":"MINH NHUNG","Description":"","Lng":107.808188796043,"Lat":11.5523520433331,"Price":null,"LocationType":0,"IsDeleted":false},{"ID":0,"Name":"Minh Nhung *","Description":"","Lng":107.808078825474,"Lat":11.552481301815,"Price":null,"LocationType":0,"IsDeleted":false},{"ID":0,"Name":"Minh Quân **","Description":"","Lng":107.811133861542,"Lat":11.5417719442095,"Price":null,"LocationType":0,"IsDeleted":false},{"ID":0,"Name":"Minh Tân* \nĐC: 54 Phan Đình Phùng, Đà Lạt\nĐT: (+84-63) 3 556262\nNNKD: Khách sạn (19 phòng)\n","Description":"","Lng":108.434018567204,"Lat":11.9438920447182,"Price":null,"LocationType":0,"IsDeleted":false},{"ID":0,"Name":"Minh Thành *\nĐC: 49 Nam Kỳ Khởi Nghĩa, Đà Lạt\nĐT: (+84-63) 3 833344\nNNKD: Khách sạn (30 phòng)\n","Description":"","Lng":108.435151129961,"Lat":11.940494416649,"Price":null,"LocationType":0,"IsDeleted":false},{"ID":0,"Name":"Mộc \nĐC: 22 Nguyễn Du - Đà Lạt\nĐT: (+84-63) 3829293\n","Description":"","Lng":108.462109342217,"Lat":11.9466900207831,"Price":null,"LocationType":0,"IsDeleted":false},{"ID":0,"Name":"Mỹ Cảnh Thành *","Description":"","Lng":108.385834693909,"Lat":11.752873647714,"Price":null,"LocationType":0,"IsDeleted":false},{"ID":0,"Name":"MỸ CẢNH THÀNH\nĐC: 129 Quốc lộ 20, Khu phố 6, TT. Liên Nghĩa\nĐT: (+84-63) 3662881\nNNKD: Nhà hàng (500 khách)\n","Description":"","Lng":108.386486470699,"Lat":11.752645734669,"Price":null,"LocationType":0,"IsDeleted":false},{"ID":0,"Name":"Mỹ Hòa *\nĐC: 20 Nam Kỳ Khởi Nghĩa, Đà Lạt\nĐT: (+84-63) 3 828123\nNNKD: Khách sạn (37 phòng)\n","Description":"","Lng":108.433985039592,"Lat":11.9406052879807,"Price":null,"LocationType":0,"IsDeleted":false},{"ID":0,"Name":"NAM GIANG 1\nĐC: xã Phú Hội\nĐT: (+84-63) 3841669\nNNKD: Nhà hàng (1.000 khách)\n","Description":"","Lng":108.346180915833,"Lat":11.6847594280333,"Price":null,"LocationType":0,"IsDeleted":false},{"ID":0,"Name":"NAM HUÊ","Description":"","Lng":107.801338434219,"Lat":11.5424168642997,"Price":null,"LocationType":0,"IsDeleted":false},{"ID":0,"Name":"Nam Kỳ *\nĐC: 11 Nam Kỳ Khởi Nghĩa, Đà Lạt\nĐT: (+84-63) 3 824493\nNNKD: Khách sạn (13 phòng)\n","Description":"","Lng":108.435868620872,"Lat":11.9408834501853,"Price":null,"LocationType":0,"IsDeleted":false},{"ID":0,"Name":"NAM PHAN","Description":"","Lng":108.448104858398,"Lat":11.9366809182035,"Price":null,"LocationType":0,"IsDeleted":false},{"ID":0,"Name":"Nâng cấp Trường Đại học Đà Lạt, Trường cao Đẳng nghề","Description":"","Lng":108.445204,"Lat":11.957191,"Price":null,"LocationType":0,"IsDeleted":false},{"ID":0,"Name":"Nghệ sĩ (Artista)\nĐC: Đường Nguyễn Chí Thanh - Đà Lạt\n","Description":"","Lng":108.436684012413,"Lat":11.9412566287897,"Price":null,"LocationType":0,"IsDeleted":false},{"ID":0,"Name":"Ngọc Giang 2 *\nĐC: 37 Nam Kỳ Khởi Nghĩa, Đà Lạt\nĐT: (+84-63) 3 510280\nNNKD: Khách sạn (13 phòng)\n","Description":"","Lng":108.435340896249,"Lat":11.9405167221376,"Price":null,"LocationType":0,"IsDeleted":false},{"ID":0,"Name":"Ngọc Giang 3 *\nĐC: 21 Nam Kỳ Khởi Nghĩa, Đà Lạt\nĐT: (+84-63) 3 511669\nNNKD: Khách sạn (14 phòng)\n","Description":"","Lng":108.435858562589,"Lat":11.9406420264001,"Price":null,"LocationType":0,"IsDeleted":false},{"ID":0,"Name":"Ngọc Mai Phú *\nĐC: 73 Nam Kỳ Khởi Nghĩa, Đà Lạt\nĐT: (+84-63) 3 510199\nNNKD: Khách sạn (30 phòng)\n","Description":"","Lng":108.434612676501,"Lat":11.9406433384864,"Price":null,"LocationType":0,"IsDeleted":false},{"ID":0,"Name":"Ngọc Như Ý *\nĐC: 25-27 Nam Kỳ Khởi Nghĩa, Đà Lạt\nĐT: (+84-63) 3 510261\nNNKD: Khách sạn (29 phòng)\n","Description":"","Lng":108.435604423285,"Lat":11.9405803583361,"Price":null,"LocationType":0,"IsDeleted":false},{"ID":0,"Name":"Ngọc Thắng *\nĐC: B7 - Đường 3/2, Đà Lạt\nĐT: (+84-63) 3 511169\nNNKD: Khách sạn (21 phòng)\n","Description":"","Lng":108.440070301294,"Lat":11.9397137237389,"Price":null,"LocationType":0,"IsDeleted":false},{"ID":0,"Name":"Ngọc Vy *","Description":"","Lng":107.823450565338,"Lat":11.537897382899,"Price":null,"LocationType":0,"IsDeleted":false},{"ID":0,"Name":"NGŨ SẮC","Description":"","Lng":108.430767059326,"Lat":11.936196094788,"Price":null,"LocationType":0,"IsDeleted":false},{"ID":0,"Name":"Nguyên Anh *\nĐC: 30 đường 3/2, Đà Lạt\nĐT: (+84-63) 3 825740\nNNKD: Khách sạn (11 phòng)\n","Description":"","Lng":108.435122296214,"Lat":11.9427944954661,"Price":null,"LocationType":0,"IsDeleted":false},{"ID":0,"Name":"Nguyên Phương *\nĐC: 28 Phan Đình Phùng, 1, Đà Lạt, Lâm Đồng, Việt Nam\nĐT: (+84-63) 3 510077\nNNKD: Khách sạn (28 phòng)\n","Description":"","Lng":108.433753028512,"Lat":11.942715770891,"Price":null,"LocationType":0,"IsDeleted":false},{"ID":0,"Name":"Nguyễn Viết Xuân","Description":"","Lng":108.429801464081,"Lat":11.9340986822812,"Price":null,"LocationType":0,"IsDeleted":false},{"ID":0,"Name":"NH Nông Nghiệp *\nĐC: 05 Nam Kỳ Khởi Nghĩa, Đà Lạt\nĐT: (+84-63) 3 826336\nNNKD: Khách sạn (12 phòng)\n","Description":"","Lng":108.436077833176,"Lat":11.9409920251997,"Price":null,"LocationType":0,"IsDeleted":false},{"ID":0,"Name":"NH Nông Nghiệp 2 *\nĐC: 69F - Đường 3/2, Đà Lạt\nĐT: (+84-63) 3 834121\nNNKD: Khách sạn (12 phòng)\n","Description":"","Lng":108.432426676154,"Lat":11.9414187804277,"Price":null,"LocationType":0,"IsDeleted":false},{"ID":0,"Name":"NHÀ HÀNG CHAY HOA SEN\nĐC: 62 Phan Đình Phùng \nĐT: (+84-63)3567999\nNNKD:  nhà hàng (100 khách)\n","Description":"","Lng":108.434111103415,"Lat":11.9445520154249,"Price":null,"LocationType":0,"IsDeleted":false},{"ID":0,"Name":"Nhà hàng NGỌC HẢI","Description":"","Lng":108.43738,"Lat":11.941195,"Price":null,"LocationType":0,"IsDeleted":false},{"ID":0,"Name":"Nhà máy xử lý chất thải rắn","Description":"","Lng":107.775822,"Lat":11.503239,"Price":null,"LocationType":0,"IsDeleted":false},{"ID":0,"Name":"Nhà máy xử lý nước thải","Description":"","Lng":107.646675,"Lat":11.417437,"Price":null,"LocationType":0,"IsDeleted":false},{"ID":0,"Name":"Nhà máy xử lý nước thải","Description":"","Lng":107.776551,"Lat":11.531329,"Price":null,"LocationType":0,"IsDeleted":false},{"ID":0,"Name":"Nhà Thờ Con Gà","Description":"","Lng":108.437833259507,"Lat":11.9365742541741,"Price":null,"LocationType":0,"IsDeleted":false},{"ID":0,"Name":"Nhật Huy *\nĐC: 2A/1 Khe Sanh, Đà Lạt\nĐT: (+84-63) 3571571\nNNKD: Khách sạn (16 phòng)\n","Description":"","Lng":108.459373489022,"Lat":11.9398127865873,"Price":null,"LocationType":0,"IsDeleted":false},{"ID":0,"Name":"Nhật Nguyên","Description":"","Lng":108.441206216812,"Lat":11.9391266718177,"Price":null,"LocationType":0,"IsDeleted":false},{"ID":0,"Name":"Nhật Tấn *\nĐC: 50 Nguyễn Chí Thanh, Đà Lạt\nĐT: (+84-63) 3 828072\nNNKD: Khách sạn (17 phòng)\n","Description":"","Lng":108.436219319701,"Lat":11.9401119430086,"Price":null,"LocationType":0,"IsDeleted":false},{"ID":0,"Name":"NHƯ NGỌC","Description":"","Lng":108.437278,"Lat":11.941604,"Price":null,"LocationType":0,"IsDeleted":false},{"ID":0,"Name":"NHƯ Ý\nĐC: 143B Phan Đình Phùng, P.2\nĐT: (+84-63) 3823770\nNNKD: nhà hàng (100 – 120 khách)\n","Description":"","Lng":108.434824571013,"Lat":11.9457558345615,"Price":null,"LocationType":0,"IsDeleted":false},{"ID":0,"Name":"OCEAN PALACE ","Description":"","Lng":108.446838,"Lat":11.926971,"Price":null,"LocationType":0,"IsDeleted":false},{"ID":0,"Name":"P&K *\nĐC: Lô B8 đường 3/2, Đà Lạt\nĐT: (+84-63) 3 510740\nNNKD: Khách sạn (16 phòng)\n","Description":"","Lng":108.454868048429,"Lat":11.942111449739,"Price":null,"LocationType":0,"IsDeleted":false},{"ID":0,"Name":"Pari*\nĐC: 18 – Phạm Ngũ Lão, Đà Lạt\nĐT: (+84-63) 3 557668\nNNKD: Khách sạn (12 phòng)\n","Description":"","Lng":108.435383141041,"Lat":11.9379351788028,"Price":null,"LocationType":0,"IsDeleted":false},{"ID":0,"Name":"Phi Phụng *","Description":"","Lng":107.804642915726,"Lat":11.5436804204894,"Price":null,"LocationType":0,"IsDeleted":false},{"ID":0,"Name":"Phố Hoa\nĐC: Đường Nguyễn Chí Thanh - Đà Lạt\n","Description":"","Lng":108.436356782913,"Lat":11.9419441595889,"Price":null,"LocationType":0,"IsDeleted":false},{"ID":0,"Name":"PHỐ NÚI","Description":"","Lng":108.436557,"Lat":11.940376,"Price":null,"LocationType":0,"IsDeleted":false},{"ID":0,"Name":"Phone","Description":"","Lng":108.443341255188,"Lat":11.9480933714738,"Price":null,"LocationType":0,"IsDeleted":false},{"ID":0,"Name":"Phong Lan *\nĐC: 128 Phan Đình Phùng, Đà Lạt\nĐT: (+84-63) 3 822594\nNNKD: Khách sạn (20 phòng)\n","Description":"","Lng":108.435282558203,"Lat":11.9466900207731,"Price":null,"LocationType":0,"IsDeleted":false},{"ID":0,"Name":"Phú Cường *\nĐC: 1A Hoàng Văn Thụ, Đà Lạt \nĐT: (+84-63) 3 821417\nNNKD: Khách sạn (11 phòng)\n","Description":"","Lng":108.426205962896,"Lat":11.9396737049761,"Price":null,"LocationType":0,"IsDeleted":false},{"ID":0,"Name":"PHÙ ĐỔNG","Description":"","Lng":108.453458547592,"Lat":11.9417613430721,"Price":null,"LocationType":0,"IsDeleted":false},{"ID":0,"Name":"PHÚ VANG","Description":"","Lng":108.430305719376,"Lat":11.9349594303219,"Price":null,"LocationType":0,"IsDeleted":false},{"ID":0,"Name":"PHÚC NGUYÊN","Description":"","Lng":108.458104133606,"Lat":11.9397669727659,"Price":null,"LocationType":0,"IsDeleted":false},{"ID":0,"Name":"Phước Đức *\nĐC: 04 Khu Hòa Bình, Đà Lạt\nĐT: (+84-63) 3 822200\nNNKD: Khách sạn (40 phòng)\n","Description":"","Lng":108.435963839293,"Lat":11.9442062854494,"Price":null,"LocationType":0,"IsDeleted":false},{"ID":0,"Name":"Phương Chi *\nĐC: 12 Nam Kỳ Khởi Nghĩa, Đà Lạt\nĐT: (+84-63) 3 824317\nNNKD: Khách sạn (36 phòng)\n","Description":"","Lng":108.435167893767,"Lat":11.9404786716141,"Price":null,"LocationType":0,"IsDeleted":false},{"ID":0,"Name":"Phương Hạnh 2 *\nĐC: 80-82 - Đuờng 3/2, Đà Lạt\nĐT: (+84-63) 3 838839\nNNKD: Khách sạn (26 phòng)\n","Description":"","Lng":108.43408562243,"Lat":11.9421030305873,"Price":null,"LocationType":0,"IsDeleted":false},{"ID":0,"Name":"Phương Mai *\nĐC: 8E Thủ Khoa Huân, Đà Lạt\nĐT: (+84-63) 3 821194\nNNKD: Khách sạn (24 phòng)\n","Description":"","Lng":108.433392941952,"Lat":11.9411320901972,"Price":null,"LocationType":0,"IsDeleted":false},{"ID":0,"Name":"Phương Nam 1 *\nĐC: 1A Hoàng Văn Thụ, Đà Lạt\nĐT: (+84-63) 3 824139\nNNKD: Khách sạn (12 phòng)\n","Description":"","Lng":108.426226079464,"Lat":11.9396782972846,"Price":null,"LocationType":0,"IsDeleted":false},{"ID":0,"Name":"Phuợng Tím\nĐC: Đường Nguyễn Chí Thanh - Đà Lạt\n","Description":"","Lng":108.436785936356,"Lat":11.941009957009,"Price":null,"LocationType":0,"IsDeleted":false},{"ID":0,"Name":"Phương Uyên*\nĐC: 28 Nguyễn Văn Trỗi, Đà Lạt\nĐT: (+84-63) 3 511686\nNNKD: Khách sạn (10 phòng)\n","Description":"","Lng":108.435668796301,"Lat":11.9452716834272,"Price":null,"LocationType":0,"IsDeleted":false},{"ID":0,"Name":"PX **","Description":"","Lng":108.434307575226,"Lat":11.9444737287299,"Price":null,"LocationType":0,"IsDeleted":false},{"ID":0,"Name":"Quang Chiến *\nĐC: 23 Bis Hai Bà Trưng, Đà Lạt\nĐT: (+84-63) 3 815851\nNNKD: Khách sạn (14 phòng)\n","Description":"","Lng":108.431644141674,"Lat":11.9516566577279,"Price":null,"LocationType":0,"IsDeleted":false},{"ID":0,"Name":"Quang Huy *\nĐC: 04 Bùi Thị Xuân, Đà Lạt\nĐT: (+84-63) 3 823513\nNNKD: Khách sạn (21 phòng)\n","Description":"","Lng":108.440187647939,"Lat":11.9440954156215,"Price":null,"LocationType":0,"IsDeleted":false},{"ID":0,"Name":"Quốc Việt *","Description":"","Lng":107.82047867775,"Lat":11.5413042468714,"Price":null,"LocationType":0,"IsDeleted":false},{"ID":0,"Name":"Quỳnh Giao *\nĐC: 12B Nam Kỳ Khởi Nghĩa, Đà Lạt\nĐT: (+84-63) 3 831716\nNNKD: Khách sạn (11 phòng)\n","Description":"","Lng":108.435188680887,"Lat":11.9404872002102,"Price":null,"LocationType":0,"IsDeleted":false},{"ID":0,"Name":"Rainny","Description":"","Lng":108.459026813507,"Lat":11.9405857160364,"Price":null,"LocationType":0,"IsDeleted":false},{"ID":0,"Name":"Red Sun **","Description":"","Lng":108.440991640091,"Lat":11.9350834250507,"Price":null,"LocationType":0,"IsDeleted":false},{"ID":0,"Name":"River Prince ","Description":"","Lng":108.434929847717,"Lat":11.9457490555901,"Price":null,"LocationType":0,"IsDeleted":false},{"ID":0,"Name":"Rum Vàng *\nĐC: 12 Phan Bội Châu, Đà Lạt\nĐT: (+84-63) 3 825677\nNNKD: Khách sạn (10 phòng)\n","Description":"","Lng":108.437055498362,"Lat":11.9442699207811,"Price":null,"LocationType":0,"IsDeleted":false},{"ID":0,"Name":"Rừng hoa Cafeteria","Description":"","Lng":108.450733423233,"Lat":11.9778759281204,"Price":null,"LocationType":0,"IsDeleted":false},{"ID":0,"Name":"Sài Gòn - Đà Lạt","Description":"","Lng":108.426217,"Lat":11.939652,"Price":null,"LocationType":0,"IsDeleted":false},{"ID":0,"Name":"Sammy","Description":"","Lng":108.432507,"Lat":11.935266,"Price":null,"LocationType":0,"IsDeleted":false},{"ID":0,"Name":"Saphir Đà Lạt **","Description":"","Lng":108.43465089798,"Lat":11.9419693078147,"Price":null,"LocationType":0,"IsDeleted":false},{"ID":0,"Name":"SEN GARDEN","Description":"","Lng":107.541732788086,"Lat":11.3835825166641,"Price":null,"LocationType":0,"IsDeleted":false},{"ID":0,"Name":"Sơn ","Description":"","Lng":108.433631658554,"Lat":11.9459789942847,"Price":null,"LocationType":0,"IsDeleted":false},{"ID":0,"Name":"Sơn Ngọc *","Description":"","Lng":107.934880256653,"Lat":11.5276203671665,"Price":null,"LocationType":0,"IsDeleted":false},{"ID":0,"Name":"Song Vy","Description":"","Lng":108.462138175964,"Lat":11.9465897577437,"Price":null,"LocationType":0,"IsDeleted":false},{"ID":0,"Name":"Suối Cát *\nĐC: 9B4 Lê Đại Hành, Đà Lạt\nĐT: (+84-63) 3 818733\nNNKD: Khách sạn (18 phòng)\n","Description":"","Lng":108.437418267131,"Lat":11.9374989054323,"Price":null,"LocationType":0,"IsDeleted":false},{"ID":0,"Name":"Sương Mai\nĐC: 08 Trần Hưng Đạo - Đà Lạt\n","Description":"","Lng":108.444907665253,"Lat":11.9358372330545,"Price":null,"LocationType":0,"IsDeleted":false},{"ID":0,"Name":"Sweet Garden","Description":"","Lng":108.461494445801,"Lat":11.9459179834661,"Price":null,"LocationType":0,"IsDeleted":false},{"ID":0,"Name":"Tâm Châu","Description":"","Lng":108.445690870285,"Lat":11.9521255997931,"Price":null,"LocationType":0,"IsDeleted":false},{"ID":0,"Name":"TÂM CHÂU","Description":"","Lng":107.796950340271,"Lat":11.5384735731936,"Price":null,"LocationType":0,"IsDeleted":false},{"ID":0,"Name":"TÂM CHÂU ĐÀ LẠT","Description":"","Lng":108.453640937805,"Lat":11.9420847708205,"Price":null,"LocationType":0,"IsDeleted":false},{"ID":0,"Name":"TÂM CHÂU\nĐC: 521 Hùng Vương\nĐT: (+84-63)  3 770373\nNNKD: nhà hàng, tiệc cưới (600 khách)\n","Description":"","Lng":108.07422503829,"Lat":11.5759613938502,"Price":null,"LocationType":0,"IsDeleted":false},{"ID":0,"Name":"TÂM ĐẮC","Description":"","Lng":108.441023826599,"Lat":11.9730565994426,"Price":null,"LocationType":0,"IsDeleted":false},{"ID":0,"Name":"Tâm Dung 1*\nĐC: 18A Nam Kỳ Khởi Nghĩa, Đà Lạt\nĐT: (+84-63) 3 837173\nNNKD: Khách sạn (26 phòng)\n","Description":"","Lng":108.434330374002,"Lat":11.940674172513,"Price":null,"LocationType":0,"IsDeleted":false},{"ID":0,"Name":"Tâm Dung 2*\nĐC: 14 Thủ Khoa Huân, Đà Lạt\nĐT: (+84-63) 3 535352\nNNKD: Khách sạn (20 phòng)\n","Description":"","Lng":108.43408562243,"Lat":11.9404439013035,"Price":null,"LocationType":0,"IsDeleted":false},{"ID":0,"Name":"Tầm Xuân *\nĐC: A3 Hải Thượng, Đà Lạt\nĐT: (+84-63) 3 818989\nNNKD: Khách sạn (22 phòng)\n","Description":"","Lng":108.431061431766,"Lat":11.9429375116909,"Price":null,"LocationType":0,"IsDeleted":false},{"ID":0,"Name":"Tân Anh*\nĐC:54 Nguyễn Chí Thanh, Đà Lạt\nĐT: (+84-63) 3825757\nNNKD: Khách sạn (12 phòng)\n","Description":"","Lng":108.436283692718,"Lat":11.9400712682601,"Price":null,"LocationType":0,"IsDeleted":false},{"ID":0,"Name":"Tân Thành Đạt *\nĐC: 15C Phan Như Thạch, Đà Lạt\nĐT: (+84-63) 3 828267\nNNKD: Khách sạn (15 phòng)\n","Description":"","Lng":108.435339555144,"Lat":11.9413282466761,"Price":null,"LocationType":0,"IsDeleted":false},{"ID":0,"Name":"Tân Thanh*\nĐC: 17 Lê Đại Hành, Đà Lạt\nĐT: (+84-63) 3 822962\nNNKD: Khách sạn (45phòng)\n","Description":"","Lng":108.437880948186,"Lat":11.9386378071348,"Price":null,"LocationType":0,"IsDeleted":false},{"ID":0,"Name":"Tân Tiến *\nĐC: 01 Phạm Ngũ Lão, Đà Lạt\nĐT: (+84-63) 3 822790\nNNKD: Khách sạn (40 phòng)\n","Description":"","Lng":108.436746373773,"Lat":11.9379161533604,"Price":null,"LocationType":0,"IsDeleted":false},{"ID":0,"Name":"Thạch Tiên *\nĐC: 65C Nguyễn Công Trứ, Đà Lạt\nĐT: (+84-63) 3 552171\nNNKD: Khách sạn (10 phòng)\n","Description":"","Lng":108.441001698375,"Lat":11.9552733617582,"Price":null,"LocationType":0,"IsDeleted":false},{"ID":0,"Name":"Thắng Lợi *","Description":"","Lng":107.8090685606,"Lat":11.5458537303918,"Price":null,"LocationType":0,"IsDeleted":false},{"ID":0,"Name":"Thắng Lợi 1 **","Description":"","Lng":108.432065248489,"Lat":11.9411914073324,"Price":null,"LocationType":0,"IsDeleted":false},{"ID":0,"Name":"Thanh Bình ","Description":"","Lng":108.437161445618,"Lat":11.9436087466778,"Price":null,"LocationType":0,"IsDeleted":false},{"ID":0,"Name":"Thanh Dung *\nĐC: 29 Nam Kỳ Khởi Nghĩa, Đà Lạt\nĐT: (+84-63) 3 828772\nNNKD: Khách sạn (11 phòng)\n","Description":"","Lng":108.435521945357,"Lat":11.9405580528627,"Price":null,"LocationType":0,"IsDeleted":false},{"ID":0,"Name":"Thanh Hoài 2 *\nĐC: 29D Phan Bội Châu, Đà Lạt\nĐT: (+84-63) 3 510550\t\nNNKD: Khách sạn (23 phòng)\n","Description":"","Lng":108.439529836178,"Lat":11.9437890471683,"Price":null,"LocationType":0,"IsDeleted":false},{"ID":0,"Name":"Thanh Hùng*\nĐC: 11A1 Phan Như Thạch, Đà Lạt\nĐT: (+84-63) 3 822907\nNNKD: Khách sạn (13phòng)\n","Description":"","Lng":108.434033319354,"Lat":11.9412101591907,"Price":null,"LocationType":0,"IsDeleted":false},{"ID":0,"Name":"Thanh Hương *\nĐC: 02 Bùi Thị Xuân, Đà Lạt\nĐT: (+84-63) 3 827699\nNNKD: Khách sạn (11 phòng)\n","Description":"","Lng":108.440458551049,"Lat":11.9434708697453,"Price":null,"LocationType":0,"IsDeleted":false},{"ID":0,"Name":"Thanh Loan 3 *\nĐC: 7A Hồ Tùng Mậu, Đà Lạt\nĐT: (+84-63) 3 531035\nNNKD: Khách sạn (25 phòng)\n","Description":"","Lng":108.4397893399,"Lat":11.9379076247134,"Price":null,"LocationType":0,"IsDeleted":false},{"ID":0,"Name":"Thành Phố Xanh*\nĐC: 174 Phan Đình Phùng, Đà Lạt\nĐT: (+84-63) 3827999\nNNKD: Khách sạn (19 phòng)\n","Description":"","Lng":108.435732498765,"Lat":11.9479404082288,"Price":null,"LocationType":0,"IsDeleted":false},{"ID":0,"Name":"Thanh Thế **","Description":"","Lng":108.435198068619,"Lat":11.9464933214996,"Price":null,"LocationType":0,"IsDeleted":false},{"ID":0,"Name":"THANH THỦY","Description":"","Lng":108.439291,"Lat":11.941722,"Price":null,"LocationType":0,"IsDeleted":false},{"ID":0,"Name":"Thanh Vân 2 *","Description":"","Lng":107.807335853577,"Lat":11.5434907149641,"Price":null,"LocationType":0,"IsDeleted":false},{"ID":0,"Name":"Thảo Liên*\nĐC: 9A1 Bùi Thị Xuân, Đà Lạt\nĐT: (+84-63) 3 832310\nNNKD: Khách sạn (24 phòng)\n","Description":"","Lng":108.43968808651,"Lat":11.94588048039,"Price":null,"LocationType":0,"IsDeleted":false},{"ID":0,"Name":"Thảo Nguyên Xanh *\nĐC: 34 Hồ Tùng Mậu, Đà Lạt\nĐT: (+84-63) 3 832508\nNNKD: Khách sạn (10 phòng)\n","Description":"","Lng":108.43945004046,"Lat":11.9386345268947,"Price":null,"LocationType":0,"IsDeleted":false},{"ID":0,"Name":"Thảo Phương *\nĐC: 51 Nguyễn Văn Trỗi, Đà Lạt\nĐT: (+84-63) 3 834480\nNNKD: Khách sạn (16 phòng)\n","Description":"","Lng":108.435775414109,"Lat":11.9458968811513,"Price":null,"LocationType":0,"IsDeleted":false},{"ID":0,"Name":"The Escape Bar","Description":"","Lng":108.43976855278,"Lat":11.9438711609407,"Price":null,"LocationType":0,"IsDeleted":false},{"ID":0,"Name":"Thi Thảo **","Description":"","Lng":108.439511060715,"Lat":11.9437761998087,"Price":null,"LocationType":0,"IsDeleted":false},{"ID":0,"Name":"Thiên Ban *","Description":"","Lng":107.806885242462,"Lat":11.5484197320341,"Price":null,"LocationType":0,"IsDeleted":false},{"ID":0,"Name":"Thiên Hà *\nĐC: 4D1 Bùi Thị Xuân, Đà Lạt\nĐT: (+84-63) 3 520111\nNNKD: Khách sạn (16 phòng)\n","Description":"","Lng":108.440178260207,"Lat":11.9441124724957,"Price":null,"LocationType":0,"IsDeleted":false},{"ID":0,"Name":"THIÊN TRANG","Description":"","Lng":107.811477184296,"Lat":11.5435823649222,"Price":null,"LocationType":0,"IsDeleted":false},{"ID":0,"Name":"Thời Đại *\nĐC: 138 Phan Đình Phùng, Đà Lạt\nĐT: (+84-63) 3 522699\nNNKD: Khách sạn (12 phòng)\n","Description":"","Lng":108.435494452715,"Lat":11.946915038459,"Price":null,"LocationType":0,"IsDeleted":false},{"ID":0,"Name":"Thol *\nĐC: 4A Hoàng Diệu, Đà Lạt\nĐT: (+84-63) 3 531234\nNNKD: Khách sạn (11 phòng)\n","Description":"","Lng":108.430373445153,"Lat":11.9426108047786,"Price":null,"LocationType":0,"IsDeleted":false},{"ID":0,"Name":"Thông Xanh *\nĐC: 33-35 Nam Kỳ Khởi Nghĩa, Đà Lạt\nĐT: (+84-63) 3 825289\nNNKD: Khách sạn (18 phòng)\n","Description":"","Lng":108.435399234295,"Lat":11.9405390276045,"Price":null,"LocationType":0,"IsDeleted":false},{"ID":0,"Name":"Thu Trang *","Description":"","Lng":108.373571634293,"Lat":11.7325332265243,"Price":null,"LocationType":0,"IsDeleted":false},{"ID":0,"Name":"Thuận Lâm *\nĐC: 20 Nguyẽn Du, Đà Lạt\nĐT: (+84-63) 3 826039\nNNKD: Khách sạn (25 phòng)\n","Description":"","Lng":108.461999371648,"Lat":11.9465686554713,"Price":null,"LocationType":0,"IsDeleted":false},{"ID":0,"Name":"Thuê xe đạp đôi","Description":"","Lng":108.437982201576,"Lat":11.9436340040617,"Price":null,"LocationType":0,"IsDeleted":false},{"ID":0,"Name":"Thuê xe mô tô","Description":"","Lng":108.437421619892,"Lat":11.9406193382532,"Price":null,"LocationType":0,"IsDeleted":false},{"ID":0,"Name":"THUNG LŨNG CÁ","Description":"","Lng":108.465378284454,"Lat":11.951124190524,"Price":null,"LocationType":0,"IsDeleted":false},{"ID":0,"Name":"THỦY TẠ","Description":"","Lng":108.448877334595,"Lat":11.9403128018878,"Price":null,"LocationType":0,"IsDeleted":false},{"ID":0,"Name":"Thy Thư *\nĐC: 12D Nam Kỳ Khởi Nghĩa, Đà Lạt\nĐT: (+84-63) 3 835866\nNNKD: Khách sạn (12 phòng)\n","Description":"","Lng":108.435167893767,"Lat":11.9405036012681,"Price":null,"LocationType":0,"IsDeleted":false},{"ID":0,"Name":"TM","Description":"","Lng":108.442686796188,"Lat":11.9591832487964,"Price":null,"LocationType":0,"IsDeleted":false},{"ID":0,"Name":"Tô Ni *","Description":"","Lng":108.435841798782,"Lat":11.9406213883883,"Price":null,"LocationType":0,"IsDeleted":false},{"ID":0,"Name":"Tô Ni *\nĐC: 08 Nam Kỳ Khởi Nghĩa, Đà Lạt\nĐT: (+84-63) 3 837226\nNNKD: Khách sạn (10 phòng)\n","Description":"","Lng":108.435850515962,"Lat":11.9406695802214,"Price":null,"LocationType":0,"IsDeleted":false},{"ID":0,"Name":"Toàn Thịnh*","Description":"","Lng":108.439886569977,"Lat":11.943870627912,"Price":null,"LocationType":0,"IsDeleted":false},{"ID":0,"Name":"Toàn Thịnh*\nĐC:4C Phan Bội Châu, Đà Lạt\nĐT: (+84-63) 3 822696\nNNKD: Khách sạn (23 phòng)\n","Description":"","Lng":108.439743742347,"Lat":11.9438749878002,"Price":null,"LocationType":0,"IsDeleted":false},{"ID":0,"Name":"Trầm Hương **","Description":"","Lng":108.436877131462,"Lat":11.947271042748,"Price":null,"LocationType":0,"IsDeleted":false},{"ID":0,"Name":"Trần Anh Trí*(Nice Dream)","Description":"","Lng":108.433256149292,"Lat":11.9459473408241,"Price":null,"LocationType":0,"IsDeleted":false},{"ID":0,"Name":"Trần Anh Trí*(Nice Dream)\nĐC: 34B Hai Bà Trưng, Đà Lạt\nĐT: (+84-63) 3 837226\nNNKD: Khách sạn (10 phòng)\n","Description":"","Lng":108.433491513133,"Lat":11.9459080336584,"Price":null,"LocationType":0,"IsDeleted":false},{"ID":0,"Name":"Trang Anh *","Description":"","Lng":108.439527153969,"Lat":11.9374356238344,"Price":null,"LocationType":0,"IsDeleted":false},{"ID":0,"Name":"Trung Cang **","Description":"","Lng":108.440256714821,"Lat":11.9441483357299,"Price":null,"LocationType":0,"IsDeleted":false},{"ID":0,"Name":"Trung Nguyên \nĐC:  53A Phù Đổng Thiên Vương - Đà Lạt\n","Description":"","Lng":108.442554026842,"Lat":11.9558021034458,"Price":null,"LocationType":0,"IsDeleted":false},{"ID":0,"Name":"Trung Quyền *","Description":"","Lng":108.372970819473,"Lat":11.7311571094969,"Price":null,"LocationType":0,"IsDeleted":false},{"ID":0,"Name":"Trung tâm chẩn đoán y khoa kỹ thuật cao và Trung tâm y học hạt nhân và xạ trị khu vực Tây Nguyên tại","Description":"","Lng":108.458977,"Lat":11.948647,"Price":null,"LocationType":0,"IsDeleted":false},{"ID":0,"Name":"TRUNG TÂM LƯU TRỮ QUỐC GIA IV\nĐC: Đường Yết Kiêu, Đà Lạt\nĐT: (+84-63) 3 561032\nNNKD: Tham quan\n","Description":"","Lng":108.426452726126,"Lat":11.9458876967251,"Price":null,"LocationType":0,"IsDeleted":false},{"ID":0,"Name":"TỪ HẠNH","Description":"","Lng":108.42493057251,"Lat":11.9394940577927,"Price":null,"LocationType":0,"IsDeleted":false},{"ID":0,"Name":"Tulip","Description":"","Lng":108.439891934395,"Lat":11.9393671128737,"Price":null,"LocationType":0,"IsDeleted":false},{"ID":0,"Name":"Tulip Xanh*","Description":"","Lng":108.430659770966,"Lat":11.9440569418848,"Price":null,"LocationType":0,"IsDeleted":false},{"ID":0,"Name":"Tùng Giang *","Description":"","Lng":107.805227637291,"Lat":11.5443264037963,"Price":null,"LocationType":0,"IsDeleted":false},{"ID":0,"Name":"Tùng\nĐC: 6 Khu Hòa Bình – Đà Lạt\n","Description":"","Lng":108.43598395586,"Lat":11.9441367457705,"Price":null,"LocationType":0,"IsDeleted":false},{"ID":0,"Name":"Tường Vy","Description":"","Lng":108.444478511811,"Lat":11.9364683570293,"Price":null,"LocationType":0,"IsDeleted":false},{"ID":0,"Name":"Uyên Vy *","Description":"","Lng":108.435187339783,"Lat":11.9377809524188,"Price":null,"LocationType":0,"IsDeleted":false},{"ID":0,"Name":"VẠN HUÊ LẦU\nĐC: 22D/1 Trần Phú, P.3\nĐT: (+84-63) 3824794\nNNKD: nhà hàng (300 khách)\n","Description":"","Lng":108.435689583421,"Lat":11.9366322609402,"Price":null,"LocationType":0,"IsDeleted":false},{"ID":0,"Name":"Văn nghệ Dương Tùng","Description":"","Lng":108.434302210808,"Lat":11.9504461953126,"Price":null,"LocationType":0,"IsDeleted":false},{"ID":0,"Name":"Văn nghệ Dương Tùng\nĐC: KQH Phan Đình Phùng – Nguyễn Công Trứ\nTel: (+84-63) 3542161- 0902 478910\n","Description":"","Lng":108.432086706161,"Lat":11.9544812310788,"Price":null,"LocationType":0,"IsDeleted":false},{"ID":0,"Name":"Vân Toàn*","Description":"","Lng":108.369247913361,"Lat":11.7262177054414,"Price":null,"LocationType":0,"IsDeleted":false},{"ID":0,"Name":"VIỆT CƯỜNG\nĐC: 26-28 Ngô Gia Tự\nĐT: (+84-63) 3844396\nNNKD: Nhà hàng (400 khách)\n","Description":"","Lng":108.374075219035,"Lat":11.7313764504794,"Price":null,"LocationType":0,"IsDeleted":false},{"ID":0,"Name":"Việt Hưng\nĐC: Đường Nguyễn Chí Thanh - Đà Lạt\n","Description":"","Lng":108.436619639397,"Lat":11.9413489119424,"Price":null,"LocationType":0,"IsDeleted":false},{"ID":0,"Name":"Vietsovpetro","Description":"","Lng":108.460184,"Lat":11.941509,"Price":null,"LocationType":0,"IsDeleted":false},{"ID":0,"Name":"Vinh Hoa *","Description":"","Lng":108.430176973343,"Lat":11.9377032924786,"Price":null,"LocationType":0,"IsDeleted":false},{"ID":0,"Name":"Vũ Nhi *","Description":"","Lng":108.43505859375,"Lat":11.9402266961048,"Price":null,"LocationType":0,"IsDeleted":false},{"ID":0,"Name":"VƯỜN QUỐC GIA BIDOUP – NÚI BÀ\nĐC: 5E Trần Hưng Đạo, P.10, Đà Lạt\nĐT: (+84-63) 3823953\n","Description":"","Lng":108.441967964172,"Lat":11.9360012467028,"Price":null,"LocationType":0,"IsDeleted":false},{"ID":0,"Name":"Why not\nĐC: Đường Nguyễn Chí Thanh - Đà Lạt\n","Description":"","Lng":108.436565995216,"Lat":11.9415242936594,"Price":null,"LocationType":0,"IsDeleted":false},{"ID":0,"Name":"Windmills","Description":"","Lng":108.434586524963,"Lat":11.9449880588035,"Price":null,"LocationType":0,"IsDeleted":false},{"ID":0,"Name":"Xe lửa trong thành phố","Description":"","Lng":108.463897705078,"Lat":11.9478168567482,"Price":null,"LocationType":0,"IsDeleted":false},{"ID":0,"Name":"Xuân Hồng *","Description":"","Lng":108.435423374176,"Lat":11.9405689049264,"Price":null,"LocationType":0,"IsDeleted":false},{"ID":0,"Name":"Xuân Hưởng","Description":"","Lng":108.437831997871,"Lat":11.948708968338,"Price":null,"LocationType":0,"IsDeleted":false},{"ID":0,"Name":"Ý Lan *","Description":"","Lng":108.432470262051,"Lat":11.9414957695676,"Price":null,"LocationType":0,"IsDeleted":false},{"ID":0,"Name":"Ý Như *","Description":"","Lng":108.435128331184,"Lat":11.9405059247588,"Price":null,"LocationType":0,"IsDeleted":false},{"ID":0,"Name":"YẾN SÀO","Description":"","Lng":108.465292453766,"Lat":11.9470725944764,"Price":null,"LocationType":0,"IsDeleted":false},{"ID":0,"Name":"YK Home *","Description":"","Lng":108.426298499107,"Lat":11.9453795049931,"Price":null,"LocationType":0,"IsDeleted":false},{"ID":0,"Name":"You & me\nĐC: Đường Nguyễn Chí Thanh - Đà Lạt\n","Description":"","Lng":108.436619639397,"Lat":11.9405743445923,"Price":null,"LocationType":0,"IsDeleted":false}]}